[
    {
        "url" : "/auth/",
        "method" : "post",
        "controller" : "api",
        "function" : "auth",
        "fields": [
        	"login",
        	"password"
        ],
        "auth": false
    },

    {
        "url" : "/reg/",
        "method" : "post",
        "controller" : "api",
        "function" : "reg",
        "fields": [
        	"login",
        	"password"
        ],
        "auth": false
    },

    {
        "url" : "/getAccount/",
        "method" : "post",
        "controller" : "api",
        "function" : "get_account",
        "auth": true
    },

    {
        "url" : "/editAccount/",
        "method" : "post",
        "controller" : "api",
        "function" : "edit_account",
        "auth": true,
        "fields": [
            "name",
            "email",
            "telephone",
            "login"
        ]
    },

    {
        "url" : "/newPromocode/",
        "method" : "post",
        "controller" : "api",
        "function" : "new_promocode",
        "level_access": 0,
        "fields": [
            "code",
            "percent"
        ]
    },

    {
        "url" : "/turnPromocode/",
        "method" : "post",
        "controller" : "api",
        "function" : "turn_promocode",
        "level_access": 0,
        "fields": [
            "id"
        ]
    },

    {
        "url" : "/newDeliveryService/",
        "method" : "post",
        "controller" : "api",
        "function" : "new_delivery_service",
        "level_access": 0,
        "fields": [
            "name",
            "title"
        ]
    },

    {
        "url" : "/removeDeliveryService/",
        "method" : "post",
        "controller" : "api",
        "function" : "remove_delivery_service",
        "level_access": 0,
        "fields": [
            "id"
        ]
    },

    {
        "url" : "/getCategorys/",
        "method" : "post",
        "controller" : "api",
        "function" : "get_categorys"
    },

    {
        "url" : "/getSubcategorys/",
        "method" : "post",
        "controller" : "api",
        "function" : "get_subcategorys",
        "fields": [
            "id"
        ]
    },

    {
        "url" : "/newProduct/",
        "method" : "post",
        "controller" : "api",
        "function" : "new_product",
        "level_access": 0,
        "fields": [
            "name",
            "description",
            "price",
            "category",
            "subcategory"
        ]
    },

    {
        "url" : "/productSaleOff/",
        "method" : "post",
        "controller" : "api",
        "function" : "product_sale_off",
        "level_access": 0,
        "fields": [
            "id"
        ]
    },

    {
        "url" : "/productRemove/",
        "method" : "post",
        "controller" : "api",
        "function" : "product_remove",
        "level_access": 0,
        "fields": [
            "id"
        ]
    },

    {
        "url" : "/productSearch/",
        "method" : "post",
        "controller" : "api",
        "function" : "product_search",
        "level_access": 0,
        "fields": [
            "query"
        ]
    },

    {
        "url" : "/productGet/",
        "method" : "post",
        "controller" : "api",
        "function" : "product_get",
        "fields": [
            "id"
        ]
    }
]